{"chunk_definitions":[{"row":50,"row_count":1,"visible":true,"expansion_state":0,"options":{"engine":"r","label":"unnamed-chunk-5"},"document_id":"8A914809","chunk_id":"c21h3o5v8lkvq","chunk_label":"unnamed-chunk-2"},{"row":59,"row_count":1,"visible":true,"expansion_state":0,"options":{"engine":"r","label":"unnamed-chunk-8"},"document_id":"8A914809","chunk_id":"c67reb6kv4hg6","chunk_label":"unnamed-chunk-3"},{"row":66,"row_count":1,"visible":true,"expansion_state":0,"options":{"engine":"r","label":"unnamed-chunk-9"},"document_id":"8A914809","chunk_id":"c1zm9zmfrh5js","chunk_label":"unnamed-chunk-4"},{"row":73,"row_count":1,"visible":true,"expansion_state":0,"options":{"engine":"r","label":"unnamed-chunk-10"},"document_id":"8A914809","chunk_id":"cjwuq6uw3b2k3","chunk_label":"unnamed-chunk-5"},{"row":85,"row_count":1,"visible":true,"expansion_state":0,"options":{"engine":"r","label":"unnamed-chunk-12"},"document_id":"8A914809","chunk_id":"cdj6mtuq9vlug","chunk_label":"unnamed-chunk-6"},{"row":91,"row_count":1,"visible":true,"expansion_state":0,"options":{"engine":"r","label":"unnamed-chunk-28"},"document_id":"8A914809","chunk_id":"c5n5195lv9fip","chunk_label":"unnamed-chunk-7"},{"row":99,"row_count":1,"visible":true,"expansion_state":0,"options":{"engine":"r","label":"unnamed-chunk-14"},"document_id":"8A914809","chunk_id":"cbrgo6hc4x6go","chunk_label":"unnamed-chunk-8"},{"row":106,"row_count":1,"visible":true,"expansion_state":0,"options":{"engine":"r","label":"unnamed-chunk-15"},"document_id":"8A914809","chunk_id":"cax6fy4vz6n6h","chunk_label":"unnamed-chunk-9"},{"row":113,"row_count":1,"visible":true,"expansion_state":0,"options":{"engine":"r","label":"unnamed-chunk-16"},"document_id":"8A914809","chunk_id":"c7xs84p7emarl","chunk_label":"unnamed-chunk-10"},{"row":132,"row_count":1,"visible":true,"expansion_state":0,"options":{"engine":"r","label":"unnamed-chunk-18"},"document_id":"8A914809","chunk_id":"c6k4ijs548jcp","chunk_label":"unnamed-chunk-11"},{"row":146,"row_count":1,"visible":true,"expansion_state":0,"options":{"engine":"r","label":"unnamed-chunk-35"},"document_id":"8A914809","chunk_id":"clf3x0w1j3t9j","chunk_label":"unnamed-chunk-12"},{"row":160,"row_count":1,"visible":true,"expansion_state":0,"options":{"engine":"r","label":"unnamed-chunk-47"},"document_id":"8A914809","chunk_id":"czmp5bbaj0mij","chunk_label":"unnamed-chunk-13"},{"row":169,"row_count":1,"visible":true,"expansion_state":0,"options":{"engine":"r","label":"unnamed-chunk-49"},"document_id":"8A914809","chunk_id":"cqsomg8vt6uac","chunk_label":"unnamed-chunk-14"}],"doc_write_time":1681135593}